{
    "directed": false, 
    "graph": {}, 
    "nodes": [
        {
            "name": "Janet L.", 
            "degree": 5, 
            "id": 0
        }, 
        {
            "name": "Louise", 
            "degree": 0, 
            "id": 1
        }, 
        {
            "name": "Pat L.", 
            "degree": 0, 
            "id": 2
        }, 
        {
            "name": "Ego", 
            "degree": 10, 
            "id": 3
        }, 
        {
            "name": "Don D.", 
            "degree": 0, 
            "id": 4
        }, 
        {
            "name": "Linda", 
            "degree": 3, 
            "id": 5
        }, 
        {
            "name": "Bob", 
            "degree": 4, 
            "id": 6
        }, 
        {
            "name": "Livi", 
            "degree": 4, 
            "id": 7
        }, 
        {
            "name": "Bernie", 
            "degree": 4, 
            "id": 8
        }, 
        {
            "name": "Mike", 
            "degree": 0, 
            "id": 9
        }, 
        {
            "name": "Mary E.", 
            "degree": 0, 
            "id": 10
        }, 
        {
            "name": "Johnny", 
            "degree": 6, 
            "id": 11
        }, 
        {
            "name": "Bruce", 
            "degree": 3, 
            "id": 12
        }, 
        {
            "name": "Libbie", 
            "degree": 0, 
            "id": 13
        }, 
        {
            "name": "Larry B.", 
            "degree": 0, 
            "id": 14
        }, 
        {
            "name": "Ted", 
            "degree": 6, 
            "id": 15
        }, 
        {
            "name": "Brenda", 
            "degree": 0, 
            "id": 16
        }, 
        {
            "name": "Jan B.", 
            "degree": 0, 
            "id": 17
        }, 
        {
            "name": "Joe", 
            "degree": 10, 
            "id": 18
        }, 
        {
            "name": "Chris", 
            "degree": 0, 
            "id": 19
        }, 
        {
            "name": "Pat D.", 
            "degree": 0, 
            "id": 20
        }, 
        {
            "name": "Paul", 
            "degree": 0, 
            "id": 21
        }, 
        {
            "name": "Angie", 
            "degree": 3, 
            "id": 22
        }, 
        {
            "name": "Marilyn", 
            "degree": 0, 
            "id": 23
        }, 
        {
            "name": "John E.", 
            "degree": 0, 
            "id": 24
        }
    ], 
    "links": [
        {
            "source": 0, 
            "target": 11, 
            "weight": 1.0
        }, 
        {
            "source": 0, 
            "target": 18, 
            "weight": 1.0
        }, 
        {
            "source": 0, 
            "target": 3, 
            "weight": 1.0
        }, 
        {
            "source": 0, 
            "target": 6, 
            "weight": 1.0
        }, 
        {
            "source": 0, 
            "target": 15, 
            "weight": 1.0
        }, 
        {
            "source": 3, 
            "target": 5, 
            "weight": 2.0
        }, 
        {
            "source": 3, 
            "target": 6, 
            "weight": 1.0
        }, 
        {
            "source": 3, 
            "target": 7, 
            "weight": 2.0
        }, 
        {
            "source": 3, 
            "target": 8, 
            "weight": 1.0
        }, 
        {
            "source": 3, 
            "target": 11, 
            "weight": 1.0
        }, 
        {
            "source": 3, 
            "target": 12, 
            "weight": 1.0
        }, 
        {
            "source": 3, 
            "target": 15, 
            "weight": 1.0
        }, 
        {
            "source": 3, 
            "target": 18, 
            "weight": 2.0
        }, 
        {
            "source": 3, 
            "target": 22, 
            "weight": 2.0
        }, 
        {
            "source": 5, 
            "target": 18, 
            "weight": 1.0
        }, 
        {
            "source": 5, 
            "target": 6, 
            "weight": 2.0
        }, 
        {
            "source": 6, 
            "target": 18, 
            "weight": 2.0
        }, 
        {
            "source": 7, 
            "target": 11, 
            "weight": 1.0
        }, 
        {
            "source": 7, 
            "target": 18, 
            "weight": 2.0
        }, 
        {
            "source": 7, 
            "target": 15, 
            "weight": 1.0
        }, 
        {
            "source": 8, 
            "target": 11, 
            "weight": 1.0
        }, 
        {
            "source": 8, 
            "target": 18, 
            "weight": 1.0
        }, 
        {
            "source": 8, 
            "target": 15, 
            "weight": 2.0
        }, 
        {
            "source": 11, 
            "target": 15, 
            "weight": 2.0
        }, 
        {
            "source": 11, 
            "target": 18, 
            "weight": 2.0
        }, 
        {
            "source": 12, 
            "target": 18, 
            "weight": 1.0
        }, 
        {
            "source": 12, 
            "target": 22, 
            "weight": 2.0
        }, 
        {
            "source": 15, 
            "target": 18, 
            "weight": 2.0
        }, 
        {
            "source": 18, 
            "target": 22, 
            "weight": 1.0
        }
    ], 
    "multigraph": false
}